CloudWatchLogs2Pandas/CloudWatchQuery.py
CloudWatchLogs2Pandas/__init__.py
CloudWatchLogs2Pandas/_modidx.py
CloudWatchLogs2Pandas/core.py
CloudWatchLogs2Pandas-0.0.2.dist-info/LICENSE
CloudWatchLogs2Pandas-0.0.2.dist-info/METADATA
CloudWatchLogs2Pandas-0.0.2.dist-info/WHEEL
CloudWatchLogs2Pandas-0.0.2.dist-info/entry_points.txt
CloudWatchLogs2Pandas-0.0.2.dist-info/top_level.txt
CloudWatchLogs2Pandas-0.0.2.dist-info/RECORD
