Metadata-Version: 2.1
Name: CloudWatchLogs2Pandas
Version: 0.0.2
Summary: Library to query CloudWatch Logs and create Pandas DataFrame from the results
Home-page: https://github.com/guyernest/CloudWatchLogs2Pandas
Author: Guy Ernest
Author-email: guy.ernest@gmail.com
License: Apache Software License 2.0
Keywords: nbdev jupyter notebook python
Platform: UNKNOWN
Classifier: Development Status :: 4 - Beta
Classifier: Intended Audience :: Developers
Classifier: Natural Language :: English
Classifier: Programming Language :: Python :: 3.7
Classifier: Programming Language :: Python :: 3.8
Classifier: Programming Language :: Python :: 3.9
Classifier: Programming Language :: Python :: 3.10
Classifier: License :: OSI Approved :: Apache Software License
Requires-Python: >=3.7
Requires-Dist: fastcore
Requires-Dist: pandas
Requires-Dist: awswrangler
Provides-Extra: dev
